{
  "total_equity": 95513.19030148658,
  "cash": 95513.19030148658,
  "positions": [
    {
      "symbol": "SOL",
      "side": "long",
      "entry_price": 81.45548387096774,
      "size": 31.0,
      "value_usd": 2631.2799999999997,
      "pnl": 106.15999999999993,
      "leverage": 2,
      "pnlPercent": 8.41
    },
    {
      "symbol": "ETH",
      "side": "short",
      "entry_price": 1958.37,
      "size": 7.0,
      "value_usd": 13909.42,
      "pnl": -20.083000000000037,
      "leverage": 2,
      "pnlPercent": -2.93
    },
    {
      "symbol": "BTC",
      "side": "short",
      "entry_price": 69458.2,
      "size": 1.0,
      "value_usd": 67786.8,
      "pnl": 16.713999999999942,
      "leverage": 2,
      "pnlPercent": 4.81
    }
  ],
  "initial_equity": 95675.90129394957,
  "start_time": "2026-02-20T06:31:15Z"
}