{
  "total_equity": 3909.6601105079435,
  "cash": 3909.6601105079435,
  "positions": [
    {
      "symbol": "ETH",
      "side": "short",
      "entry_price": 2062.05,
      "size": 0.27599999999999997,
      "value_usd": 568.7531999999999,
      "pnl": 0.3726000000001004,
      "leverage": 3,
      "pnlPercent": 0.2
    },
    {
      "symbol": "SOL",
      "side": "long",
      "entry_price": 88.03,
      "size": 9.09,
      "value_usd": 789.6483000000001,
      "pnl": -10.54439999999997,
      "leverage": 3,
      "pnlPercent": -3.95
    }
  ],
  "initial_equity": 3905.0,
  "start_time": "2026-02-22T00:00:00Z"
}