{
  "eth": {
    "stats": {
      "sentiment_score": 0.07,
      "stablecoin_net_flow": 14832143.611758001,
      "token_net_flow": 1244046.3604268536,
      "whale_count": 59,
      "avg_tx_size": 1614765.0438391538,
      "total_volume": 103344962.80570585,
      "top_whale": {
        "address": "0x09c3385bcb373b00451d4766c13c9c3432e31e55",
        "volume": 41000001.0,
        "label": "0x09c3...1e55"
      }
    },
    "stats_24h": {
      "sentiment_score": 0.22425651685382378,
      "stablecoin_net_flow": 14832143.611758001,
      "token_net_flow": 1244046.3604268536,
      "whale_count": 59,
      "avg_tx_size": 1614765.0438391538,
      "total_volume": 103344962.80570585,
      "top_whale": {
        "address": "0x09c3385bcb373b00451d4766c13c9c3432e31e55",
        "volume": 41000001.0,
        "label": "0x09c3...1e55"
      }
    },
    "top_txs": [
      {
        "hash": "0xacdb2290b8f5679b94cebdcb3fa0685587d3667f44ac32f3890fce8640253c1f",
        "timestamp": "2025-12-19T04:00:35.000Z",
        "symbol": "USDT",
        "amount": 235097.82,
        "amount_usd": 235097.82,
        "from": "0x9ec869ed7c7a0431b99a6448aaee8f8290b20e62",
        "to": "0x649f3790686601f6a669c29a4ed4abbb23f6d9cb",
        "from_label": "0x9ec8...",
        "to_label": "0x649f...",
        "signal": "NEUTRAL",
        "chain": "ETH"
      },
      {
        "hash": "0xa80e4d0b72ad1bcf48141caa08dc713d75a667800551c1b997f607ea5581b3a2",
        "timestamp": "2025-12-19T04:00:35.000Z",
        "symbol": "USDT",
        "amount": 333000.0,
        "amount_usd": 333000.0,
        "from": "0x2eb764cadd03c781f374a6c0b4b106ae3d961d5e",
        "to": "0x28c6c06298d514db089934071355e5743bf21d60",
        "from_label": "0x2eb7...",
        "to_label": "Binance 14",
        "signal": "BULLISH_INFLOW",
        "chain": "ETH"
      },
      {
        "hash": "0xc24e2ea5e38bf3a513498e197d9438b29dc057d40bd9b9efe54b7d73ba96049a",
        "timestamp": "2025-12-19T04:00:35.000Z",
        "symbol": "USDT",
        "amount": 454000.0,
        "amount_usd": 454000.0,
        "from": "0x8be6010355efbfbb90cc06334a6027fccb1f0f79",
        "to": "0x28c6c06298d514db089934071355e5743bf21d60",
        "from_label": "0x8be6...",
        "to_label": "Binance 14",
        "signal": "BULLISH_INFLOW",
        "chain": "ETH"
      },
      {
        "hash": "0x09e30ef39ea824e8f68d01e2a86e7c17dedcf8eaff42f36292886d2ac0b7ba7a",
        "timestamp": "2025-12-19T04:00:35.000Z",
        "symbol": "USDT",
        "amount": 410000.0,
        "amount_usd": 410000.0,
        "from": "0x0f93ac65fc7109bcfedfc12ff75fc7555b8b35cf",
        "to": "0x28c6c06298d514db089934071355e5743bf21d60",
        "from_label": "0x0f93...",
        "to_label": "Binance 14",
        "signal": "BULLISH_INFLOW",
        "chain": "ETH"
      },
      {
        "hash": "0x5b303ee4cb9265c0b42a5028e6b857fbd13cd5c0bd18027d8b14940bbb85cb4c",
        "timestamp": "2025-12-19T04:00:35.000Z",
        "symbol": "USDT",
        "amount": 10000000.0,
        "amount_usd": 10000000.0,
        "from": "0x3284ac109eb04f070b40ea2bdc644d3a00de7bdb",
        "to": "0x28c6c06298d514db089934071355e5743bf21d60",
        "from_label": "0x3284...",
        "to_label": "Binance 14",
        "signal": "BULLISH_INFLOW",
        "chain": "ETH"
      },
      {
        "hash": "0x2a28b7ad3a5913dbabd24c250f112909202ef7774e0af82f0438029e4eb39f4c",
        "timestamp": "2025-12-19T04:00:35.000Z",
        "symbol": "USDT",
        "amount": 3500000.0,
        "amount_usd": 3500000.0,
        "from": "0x447f846db92e1fe2390156a285e2d2baf6a2f16c",
        "to": "0x28c6c06298d514db089934071355e5743bf21d60",
        "from_label": "0x447f...",
        "to_label": "Binance 14",
        "signal": "BULLISH_INFLOW",
        "chain": "ETH"
      },
      {
        "hash": "0xeecacf85fa841428dc583a09fb1612978e87a098a9fced52f69290f20b7712ea",
        "timestamp": "2025-12-19T04:00:35.000Z",
        "symbol": "USDT",
        "amount": 78125.0,
        "amount_usd": 78125.0,
        "from": "0xe214c63a35f335c4a3c3089b03aac7496db27ed6",
        "to": "0x28c6c06298d514db089934071355e5743bf21d60",
        "from_label": "0xe214...",
        "to_label": "Binance 14",
        "signal": "BULLISH_INFLOW",
        "chain": "ETH"
      },
      {
        "hash": "0x58fc48c694002f6ca992ed9a38a60f3fe2edec188ea2d520a44714ebe47a849f",
        "timestamp": "2025-12-19T04:00:35.000Z",
        "symbol": "USDC",
        "amount": 10000000.0,
        "amount_usd": 10000000.0,
        "from": "0xec629b4e9abc9d2399e44ec35e15af919fe09bb4",
        "to": "0xee7ae85f2fe2239e27d9c1e23fffe168d63b4055",
        "from_label": "0xec62...",
        "to_label": "0xee7a...",
        "signal": "NEUTRAL",
        "chain": "ETH"
      },
      {
        "hash": "0xaa06801c0691a36a50198b9b255092a656d33fa72ba62e1af1246b7fff163808",
        "timestamp": "2025-12-19T04:00:35.000Z",
        "symbol": "USDC",
        "amount": 112452.889467,
        "amount_usd": 112452.889467,
        "from": "0x5f3ecae36e842ffb263b013ff783658a826e7a42",
        "to": "0xee7ae85f2fe2239e27d9c1e23fffe168d63b4055",
        "from_label": "0x5f3e...",
        "to_label": "0xee7a...",
        "signal": "NEUTRAL",
        "chain": "ETH"
      },
      {
        "hash": "0xf6044f026ef238772281f8ed66b1cf90fc1816aac292b6322a0526cf64d0eb67",
        "timestamp": "2025-12-19T04:00:35.000Z",
        "symbol": "USDC",
        "amount": 50000.0,
        "amount_usd": 50000.0,
        "from": "0xbabe777e1a43053c273bd8a4e45d0cb6c20f8fc6",
        "to": "0xc026395860db2d07ee33e05fe50ed7bd583189c7",
        "from_label": "0xbabe...",
        "to_label": "0xc026...",
        "signal": "NEUTRAL",
        "chain": "ETH"
      },
      {
        "hash": "0xefef51ac23c477cd07356605c7d847fa6901c53ca86e7ebccfa770af74ff382b",
        "timestamp": "2025-12-19T03:59:35.000Z",
        "symbol": "PEPE",
        "amount": 19904947399.36,
        "amount_usd": 76001.7056741158,
        "from": "0xe9a911b75ff5bb6e7b41a045b4d3ceedb6101381",
        "to": "0xe40d7f9ca3d1cf3a4f6f64659c3a7341b5d59455",
        "from_label": "0xe9a9...",
        "to_label": "0xe40d...",
        "signal": "NEUTRAL",
        "chain": "ETH"
      },
      {
        "hash": "0xdfb2427f1006de0969e5e4d0e1e2f81cecc74a7ae531fbedfc95514dc2aea974",
        "timestamp": "2025-12-19T03:59:23.000Z",
        "symbol": "WBTC",
        "amount": 1.5678017,
        "amount_usd": 135875.552490595,
        "from": "0x51c72848c68a965f66fa7a88855f9f7784502a7f",
        "to": "0x52aa899454998be5b000ad077a46bbe360f4e497",
        "from_label": "0x51c7...",
        "to_label": "0x52aa...",
        "signal": "NEUTRAL",
        "chain": "ETH"
      },
      {
        "hash": "0xc3a7eee28a1252b8d4ba336b25609e6a1610b30a9a123978f614d944e4aa6b24",
        "timestamp": "2025-12-19T03:58:35.000Z",
        "symbol": "WBTC",
        "amount": 2.0,
        "amount_usd": 173332.5745093847,
        "from": "0xb17b3f999c9f6181cd2a573cdfdb119ee1158a6b",
        "to": "0x7d7327624bf9627fc11f6da240db8066c4beb3c8",
        "from_label": "0xb17b...",
        "to_label": "0x7d73...",
        "signal": "NEUTRAL",
        "chain": "ETH"
      },
      {
        "hash": "0xe9fc86800fa156aa51bd004a9e39b33f96a040bd9ed9af4050d966d4e753dd7f",
        "timestamp": "2025-12-19T03:41:35.000Z",
        "symbol": "PEPE",
        "amount": 14103385520.196215,
        "amount_usd": 53849.99687811299,
        "from": "0x5dd609db6eaa50d1b61d8ceffa1478b6dbd55e44",
        "to": "0x39a33fb8bf380496201e0fc95c0026f85876e24a",
        "from_label": "0x5dd6...",
        "to_label": "0x39a3...",
        "signal": "NEUTRAL",
        "chain": "ETH"
      },
      {
        "hash": "0xcc444ee47dc2df8b08d9f79b5ce6e6e94111d135d86f352f0792eab7949fe27f",
        "timestamp": "2025-12-19T00:00:11.000Z",
        "symbol": "WBTC",
        "amount": 14.60987,
        "amount_usd": 1246443.565583528,
        "from": "0xe91b373212f8ae32925cbcf39ab3a7b0763c27c9",
        "to": "0x28c6c06298d514db089934071355e5743bf21d60",
        "from_label": "0xe91b...",
        "to_label": "Binance 14",
        "signal": "BEARISH_INFLOW",
        "chain": "ETH"
      },
      {
        "hash": "0xa9515ad30abfe686324143377eeb57d911c39c5f6524a94df848ee7a4fdb6526",
        "timestamp": "2025-12-19T00:00:11.000Z",
        "symbol": "WBTC",
        "amount": 1.68318469,
        "amount_usd": 143601.19060191538,
        "from": "0x51c72848c68a965f66fa7a88855f9f7784502a7f",
        "to": "0x52aa899454998be5b000ad077a46bbe360f4e497",
        "from_label": "0x51c7...",
        "to_label": "0x52aa...",
        "signal": "NEUTRAL",
        "chain": "ETH"
      },
      {
        "hash": "0xfd28ff3ba8162821e48dd46d06634ffcc6e256db0f144393c6e153cd95cfedda",
        "timestamp": "2025-12-18T23:57:47.000Z",
        "symbol": "WBTC",
        "amount": 1.41398332,
        "amount_usd": 120634.22953499481,
        "from": "0x51c72848c68a965f66fa7a88855f9f7784502a7f",
        "to": "0x52aa899454998be5b000ad077a46bbe360f4e497",
        "from_label": "0x51c7...",
        "to_label": "0x52aa...",
        "signal": "NEUTRAL",
        "chain": "ETH"
      },
      {
        "hash": "0x27eb1d229769e4968fa33f71f0f3242e6972f0fedf9b1c7788a8e444d53c8784",
        "timestamp": "2025-12-18T23:55:47.000Z",
        "symbol": "WBTC",
        "amount": 14.60987,
        "amount_usd": 1246443.565583528,
        "from": "0xa3222357a0eccf60c73606170be6c99adecb59b3",
        "to": "0xe91b373212f8ae32925cbcf39ab3a7b0763c27c9",
        "from_label": "0xa322...",
        "to_label": "0xe91b...",
        "signal": "NEUTRAL",
        "chain": "ETH"
      },
      {
        "hash": "0x580bacb8f311d8043f5232ff96cb017f07caf780ce156be1effb371e514b2d3d",
        "timestamp": "2025-12-18T23:52:35.000Z",
        "symbol": "WBTC",
        "amount": 1.36036659,
        "amount_usd": 116059.90901632288,
        "from": "0x5ee5bf7ae06d1be5997a1a72006fe6c607ec6de8",
        "to": "0x3998f134d6aaa2b6a5f723806d00fd2bbbbce891",
        "from_label": "0x5ee5...",
        "to_label": "0x3998...",
        "signal": "NEUTRAL",
        "chain": "ETH"
      },
      {
        "hash": "0x7566c2aa0fe4e255232f97054e5085e14971d31f701bd99726269d96baf30620",
        "timestamp": "2025-12-18T23:38:23.000Z",
        "symbol": "PEPE",
        "amount": 20025427507.20053,
        "amount_usd": 74256.24506569222,
        "from": "0x5bdf85216ec1e38d6458c870992a69e38e03f7ef",
        "to": "0x0529ea5885702715e83923c59746ae8734c553b7",
        "from_label": "0x5bdf...",
        "to_label": "0x0529...",
        "signal": "NEUTRAL",
        "chain": "ETH"
      },
      {
        "hash": "0x652a5467ad59aa19dc0e24dbf5b3739e3a27475bbf3d54035a8ac072e64b8664",
        "timestamp": "2025-12-18T20:00:35.000Z",
        "symbol": "USDT",
        "amount": 84742.403,
        "amount_usd": 84742.403,
        "from": "0xa4f04533d751bb21f7caa2c224a9195da1ff7120",
        "to": "0x559432e18b281731c054cd703d4b49872be4ed53",
        "from_label": "0xa4f0...",
        "to_label": "OKX 5",
        "signal": "BULLISH_INFLOW",
        "chain": "ETH"
      },
      {
        "hash": "0xb5aa99eb10c44ab12d7d688e03691329322af685e8834e95d0863cd022b9cd6a",
        "timestamp": "2025-12-18T20:00:35.000Z",
        "symbol": "USDT",
        "amount": 87723.791242,
        "amount_usd": 87723.791242,
        "from": "0x559432e18b281731c054cd703d4b49872be4ed53",
        "to": "0x378b2e1040ea9affc8e7dc6fe1391e8504089aa0",
        "from_label": "OKX 5",
        "to_label": "0x378b...",
        "signal": "BEARISH_OUTFLOW",
        "chain": "ETH"
      },
      {
        "hash": "0xeaf6dc14a63380db959f022c734cea617e38961308bc0aec0b11452b22cd3224",
        "timestamp": "2025-12-18T20:00:35.000Z",
        "symbol": "USDC",
        "amount": 1116770.0,
        "amount_usd": 1116770.0,
        "from": "0x77f7b398a23ef4cab31dd5503fd8446c4480c70b",
        "to": "0x77134cbc06cb00b66f4c7e623d5fdbf6777635ec",
        "from_label": "0x77f7...",
        "to_label": "0x7713...",
        "signal": "NEUTRAL",
        "chain": "ETH"
      },
      {
        "hash": "0x169a4d748948c63f9986ffb674a3baaf373a973ba0cd15fcc7460e5f4c6dcae3",
        "timestamp": "2025-12-18T20:00:35.000Z",
        "symbol": "USDC",
        "amount": 269658.0,
        "amount_usd": 269658.0,
        "from": "0x93228d328c9c74c2bfe9f97638bbb5ef322f2bd5",
        "to": "0xf8191d98ae98d2f7abdfb63a9b0b812b93c873aa",
        "from_label": "0x9322...",
        "to_label": "0xf819...",
        "signal": "NEUTRAL",
        "chain": "ETH"
      },
      {
        "hash": "0x42a87e05d272fba6c6b4669c06757efdfc935647539261df646c23847cbe39be",
        "timestamp": "2025-12-18T20:00:35.000Z",
        "symbol": "WETH",
        "amount": 20.706057443790296,
        "amount_usd": 57671.33715550235,
        "from": "0x4d5f47fa6a74757f35c14fd3a6ef8e3c9bc514e8",
        "to": "0xd01607c3c5ecaba394d8be377a08590149325722",
        "from_label": "0x4d5f...",
        "to_label": "0xd016...",
        "signal": "NEUTRAL",
        "chain": "ETH"
      },
      {
        "hash": "0x7d561ef50423825a33aac2d69c8fc3c1bf922b067a0dc8013052aab45982da9a",
        "timestamp": "2025-12-18T20:00:35.000Z",
        "symbol": "WBTC",
        "amount": 3.20216248,
        "amount_usd": 270307.6081990319,
        "from": "0x8bf6c2a7cb002c7cf650c382c05fc3d665eac005",
        "to": "0xd76aa47f1ad6ce7f78ddcd4643a85c87b7e7c047",
        "from_label": "0x8bf6...",
        "to_label": "0xd76a...",
        "signal": "NEUTRAL",
        "chain": "ETH"
      },
      {
        "hash": "0xad7ce5b1f7f72a05c726b68b37e89247399b35bf27c9392703177ab710253225",
        "timestamp": "2025-12-18T20:00:23.000Z",
        "symbol": "USDT",
        "amount": 50000.0,
        "amount_usd": 50000.0,
        "from": "0x2bc6457374432452c60bf2ad26c4f07e49e0d6f5",
        "to": "0xddc825ff562647dcf4317b31191166b509ebeae7",
        "from_label": "0x2bc6...",
        "to_label": "0xddc8...",
        "signal": "NEUTRAL",
        "chain": "ETH"
      },
      {
        "hash": "0x0c99c56d9d43be68eeedcb8c84f4622e7c12799f4121d3e8fa728176f27091da",
        "timestamp": "2025-12-18T20:00:23.000Z",
        "symbol": "USDC",
        "amount": 540005.13,
        "amount_usd": 540005.13,
        "from": "0xc288fe38c2704f4b85905b45ae5d894db6c7b4b2",
        "to": "0x1c31f725c6fd84ec2e561b70e8b6f26408ba46bb",
        "from_label": "0xc288...",
        "to_label": "0x1c31...",
        "signal": "NEUTRAL",
        "chain": "ETH"
      },
      {
        "hash": "0xf0922a6eebad049e55ed097030ee42d6d56535c3f3d12a839a9c75c3fc5c1168",
        "timestamp": "2025-12-18T20:00:11.000Z",
        "symbol": "USDC",
        "amount": 250250.0,
        "amount_usd": 250250.0,
        "from": "0x67a166d92e868ceeecaea5cf3a6ab3ab6bf91260",
        "to": "0x55fe002aeff02f77364de339a1292923a15844b8",
        "from_label": "0x67a1...",
        "to_label": "0x55fe...",
        "signal": "NEUTRAL",
        "chain": "ETH"
      },
      {
        "hash": "0xc7b84400d2cdaae96ad11c8c9d0e63efde64f8b4fac778085e8f5c4512e37fa2",
        "timestamp": "2025-12-18T20:00:11.000Z",
        "symbol": "USDC",
        "amount": 530000.0,
        "amount_usd": 530000.0,
        "from": "0x0000000000000000000000000000000000000000",
        "to": "0x55fe002aeff02f77364de339a1292923a15844b8",
        "from_label": "0x0000...",
        "to_label": "0x55fe...",
        "signal": "NEUTRAL",
        "chain": "ETH"
      },
      {
        "hash": "0x5dece56910d6d9e065005b59fde98e09c51794255c8e19286656da3bf0f2f48c",
        "timestamp": "2025-12-18T19:59:35.000Z",
        "symbol": "LINK",
        "amount": 10080.923661800001,
        "amount_usd": 119603.67713687528,
        "from": "0xb762ee2bd56a78f958156f7958c60cc4725f3022",
        "to": "0xb51bf9029d778899d42e96ebcdc0498bd061006d",
        "from_label": "0xb762...",
        "to_label": "0xb51b...",
        "signal": "NEUTRAL",
        "chain": "ETH"
      },
      {
        "hash": "0xc6d5b4d26369fb0a1ee6aa0464f9dc0ddeebd56ffd233b9420adce0e2b6b85a1",
        "timestamp": "2025-12-18T19:58:59.000Z",
        "symbol": "LINK",
        "amount": 4273.84931932,
        "amount_usd": 50706.474056200896,
        "from": "0x0529ea5885702715e83923c59746ae8734c553b7",
        "to": "0x765441843bb4761baf8a587128bbeed69b63a8c6",
        "from_label": "0x0529...",
        "to_label": "0x7654...",
        "signal": "NEUTRAL",
        "chain": "ETH"
      },
      {
        "hash": "0x8c103a88d249e744bc7e2bdbc4b43f463913c2277d251cb270dd1f3268863827",
        "timestamp": "2025-12-18T19:58:35.000Z",
        "symbol": "WBTC",
        "amount": 1.08562894,
        "amount_usd": 91642.37105265511,
        "from": "0x6ff359e8fcbd54327549d4f36a850825050f2b01",
        "to": "0x9008d19f58aabd9ed0d60971565aa8510560ab41",
        "from_label": "0x6ff3...",
        "to_label": "0x9008...",
        "signal": "NEUTRAL",
        "chain": "ETH"
      },
      {
        "hash": "0x541a7937c6f1bb53957188dafead5e0475c68a1005f034ae66194ece5e8cd626",
        "timestamp": "2025-12-18T19:57:47.000Z",
        "symbol": "SHIB",
        "amount": 8076241882.207302,
        "amount_usd": 56755.63255086425,
        "from": "0xd3c56027ea70f290663b947256508fbb90d88e54",
        "to": "0x02e2201576fbbefb52812f2ee7f08eb4774b481e",
        "from_label": "0xd3c5...",
        "to_label": "0x02e2...",
        "signal": "NEUTRAL",
        "chain": "ETH"
      },
      {
        "hash": "0x55d7cd11934d6ac901e06ebe8d1088154833c335ccde111058c0fceedfde920d",
        "timestamp": "2025-12-18T19:56:35.000Z",
        "symbol": "LINK",
        "amount": 16100.075550234284,
        "amount_usd": 191017.0439328265,
        "from": "0x0d402f421baa1104320f2054074deff1de1bd1ba",
        "to": "0x5e8c8a7243651db1384c0ddfdbe39761e8e7e51a",
        "from_label": "0x0d40...",
        "to_label": "0x5e8c...",
        "signal": "NEUTRAL",
        "chain": "ETH"
      },
      {
        "hash": "0x16083b1ff41939e484cf0054ebcdffdfadfadbedd2993cb9e8235c4ffee6cc6f",
        "timestamp": "2025-12-18T19:55:47.000Z",
        "symbol": "LINK",
        "amount": 16100.075550234284,
        "amount_usd": 191017.0439328265,
        "from": "0xa6cc3c2531fdaa6ae1a3ca84c2855806728693e8",
        "to": "0xc36442b4a4522e871399cd717abdd847ab11fe88",
        "from_label": "0xa6cc...",
        "to_label": "0xc364...",
        "signal": "NEUTRAL",
        "chain": "ETH"
      },
      {
        "hash": "0xb36e13b68131ebe38dbab4f50f7811c9ec7e82198ce98cc9753df45304a824ac",
        "timestamp": "2025-12-18T19:50:11.000Z",
        "symbol": "SHIB",
        "amount": 8133226806.3,
        "amount_usd": 57156.092995204,
        "from": "0x4bf9663370a10a8ddef5f68748700e1fbe3ee8c8",
        "to": "0xd3c56027ea70f290663b947256508fbb90d88e54",
        "from_label": "0x4bf9...",
        "to_label": "0xd3c5...",
        "signal": "NEUTRAL",
        "chain": "ETH"
      },
      {
        "hash": "0x03dabf8fe75402ca6768df557ba7191b237b1986587ed08069a6b15e4873e600",
        "timestamp": "2025-12-18T19:46:47.000Z",
        "symbol": "SHIB",
        "amount": 26560649031.0,
        "amount_usd": 186654.4438245455,
        "from": "0x05afc3caee85fa79275d87961ad1511323255dfc",
        "to": "0x28c6c06298d514db089934071355e5743bf21d60",
        "from_label": "0x05af...",
        "to_label": "Binance 14",
        "signal": "BEARISH_INFLOW",
        "chain": "ETH"
      },
      {
        "hash": "0xbc640c869727cbe5720a6fae3867c458267b3becf00168b4e0d51354008c7daa",
        "timestamp": "2025-12-18T19:44:47.000Z",
        "symbol": "SHIB",
        "amount": 8849572544.0,
        "amount_usd": 62190.19871680817,
        "from": "0xe401a6a38024d8f5ab88f1b08cad476ccaca45e8",
        "to": "0x651641299c7ec0aa44ad7ed9b7e12702fed2022f",
        "from_label": "0xe401...",
        "to_label": "0x6516...",
        "signal": "NEUTRAL",
        "chain": "ETH"
      },
      {
        "hash": "0xf727eefa78b33888ea5707adba73f35dc3dfe7f064d4fc6266c59cb421dee27a",
        "timestamp": "2025-12-18T19:39:23.000Z",
        "symbol": "SHIB",
        "amount": 8133226805.299999,
        "amount_usd": 57156.09298817652,
        "from": "0x21a31ee1afc51d94c2efccaa2092ad1028285549",
        "to": "0x4bf9663370a10a8ddef5f68748700e1fbe3ee8c8",
        "from_label": "Binance 15",
        "to_label": "0x4bf9...",
        "signal": "BULLISH_OUTFLOW",
        "chain": "ETH"
      },
      {
        "hash": "0xda082c56e876b519217d9368c4b2ae38c4ef93362ecd6704dce316d985ed1ad6",
        "timestamp": "2025-12-18T16:00:35.000Z",
        "symbol": "USDT",
        "amount": 112747.58,
        "amount_usd": 112747.58,
        "from": "0x058fe98bf5b76c9267d6a4687af75da044c07aeb",
        "to": "0xd318fc61ddc61123c93cfc7ff4d451fb91239ab4",
        "from_label": "0x058f...",
        "to_label": "0xd318...",
        "signal": "NEUTRAL",
        "chain": "ETH"
      },
      {
        "hash": "0xe46aaaa243f78b3a47f51cea8577fbd4f1bb1d448b35397101deeb0db7a9c018",
        "timestamp": "2025-12-18T16:00:35.000Z",
        "symbol": "USDT",
        "amount": 2130000.0,
        "amount_usd": 2130000.0,
        "from": "0x58b704065b7aff3ed351052f8560019e05925023",
        "to": "0xa01aa2196724a39290f465b3925e5dcafe7f2256",
        "from_label": "0x58b7...",
        "to_label": "0xa01a...",
        "signal": "NEUTRAL",
        "chain": "ETH"
      },
      {
        "hash": "0x6b11830768f4d932995cb2fdcf1c749d71cb9c3772005182f1d5bbb28d161e68",
        "timestamp": "2025-12-18T16:00:35.000Z",
        "symbol": "USDT",
        "amount": 115000.0,
        "amount_usd": 115000.0,
        "from": "0xf6266e3993eb308200140278695fc6146f0d3c4d",
        "to": "0x85dc722099d128ac8d22515a8ad56985c9985c1b",
        "from_label": "0xf626...",
        "to_label": "0x85dc...",
        "signal": "NEUTRAL",
        "chain": "ETH"
      },
      {
        "hash": "0x81577f87b9f7cc200b2c8a4020a164f7b2df4be750fc9b297189a5e55deebe68",
        "timestamp": "2025-12-18T16:00:35.000Z",
        "symbol": "WBTC",
        "amount": 178.19864889,
        "amount_usd": 15727039.091581112,
        "from": "0x00eb00c6f847740000884d00e03f00c761998feb",
        "to": "0xbb2b8038a1640196fbe3e38816f3e67cba72d940",
        "from_label": "0x00eb...",
        "to_label": "0xbb2b...",
        "signal": "NEUTRAL",
        "chain": "ETH"
      },
      {
        "hash": "0xeef638bf883f3285fe4bfcbc040451f5d84a360983092da9c3c0356f62eea1f6",
        "timestamp": "2025-12-18T16:00:35.000Z",
        "symbol": "USDC",
        "amount": 233159.062,
        "amount_usd": 233159.062,
        "from": "0x975e85e8739fef9038eebe44de7924e1a055c6e2",
        "to": "0x74aa5387681505c806ff1e972b12cdfd01406828",
        "from_label": "0x975e...",
        "to_label": "0x74aa...",
        "signal": "NEUTRAL",
        "chain": "ETH"
      },
      {
        "hash": "0xb7b53e50a671259f1555bd8f4ec11993a1e57bb979e7019f556f998389efa70f",
        "timestamp": "2025-12-18T16:00:35.000Z",
        "symbol": "USDC",
        "amount": 41000001.0,
        "amount_usd": 41000001.0,
        "from": "0x09c3385bcb373b00451d4766c13c9c3432e31e55",
        "to": "0x55fe002aeff02f77364de339a1292923a15844b8",
        "from_label": "0x09c3...",
        "to_label": "0x55fe...",
        "signal": "NEUTRAL",
        "chain": "ETH"
      },
      {
        "hash": "0xda83ee93c8bccfd5a21e02ab6a0e3ad2edf011db2bb1f6cee525a4c7941997c9",
        "timestamp": "2025-12-18T16:00:35.000Z",
        "symbol": "USDC",
        "amount": 100000.0,
        "amount_usd": 100000.0,
        "from": "0xe791518e6260b8babcd58f692ff252c3babac8d1",
        "to": "0xee7ae85f2fe2239e27d9c1e23fffe168d63b4055",
        "from_label": "0xe791...",
        "to_label": "0xee7a...",
        "signal": "NEUTRAL",
        "chain": "ETH"
      },
      {
        "hash": "0x560e34b094901ae716ecf3acae53d0a76db0ccb53293e79067c281cffca6879e",
        "timestamp": "2025-12-18T16:00:35.000Z",
        "symbol": "USDC",
        "amount": 159469.828396,
        "amount_usd": 159469.828396,
        "from": "0x88bbcaeeaf0dca4ad50e8aab9387cd78c60be758",
        "to": "0xee7ae85f2fe2239e27d9c1e23fffe168d63b4055",
        "from_label": "0x88bb...",
        "to_label": "0xee7a...",
        "signal": "NEUTRAL",
        "chain": "ETH"
      },
      {
        "hash": "0x8fe858f31e1ce739622b28d50ae003e1016e2642ea0438eb8e7b1a76a67ac0b1",
        "timestamp": "2025-12-18T16:00:35.000Z",
        "symbol": "USDC",
        "amount": 1095870.106917,
        "amount_usd": 1095870.106917,
        "from": "0xb225bfe30aab7214274c33555ce01d2bdc29188a",
        "to": "0xee7ae85f2fe2239e27d9c1e23fffe168d63b4055",
        "from_label": "0xb225...",
        "to_label": "0xee7a...",
        "signal": "NEUTRAL",
        "chain": "ETH"
      },
      {
        "hash": "0xe570af1d766b8b0cfbe82951368a96caf2ed00620a1cf87bdae6dcf2f5c04f7a",
        "timestamp": "2025-12-18T16:00:35.000Z",
        "symbol": "USDC",
        "amount": 7000001.0,
        "amount_usd": 7000001.0,
        "from": "0x9a21cf1552630a00eed185f3aaf7af3751226e42",
        "to": "0xee7ae85f2fe2239e27d9c1e23fffe168d63b4055",
        "from_label": "0x9a21...",
        "to_label": "0xee7a...",
        "signal": "NEUTRAL",
        "chain": "ETH"
      }
    ]
  },
  "sol": {
    "stats": {
      "sentiment_score": 0.48,
      "stablecoin_net_flow": -333896.0505036626,
      "token_net_flow": 86122.47821424196,
      "whale_count": 28,
      "avg_tx_size": 17494.160690789548,
      "total_volume": 1259579.5697368474,
      "top_whale": {
        "address": "FjWzArnETRCpt3JxwyrFhzSYtKdzdiPRh8zVxWxhhBtQ",
        "volume": 296257.47743987804,
        "label": "FjWzAr...hBtQ"
      }
    },
    "stats_24h": {
      "sentiment_score": 0.4213639963021105,
      "stablecoin_net_flow": -333896.0505036626,
      "token_net_flow": 86122.47821424196,
      "whale_count": 28,
      "avg_tx_size": 17494.160690789548,
      "total_volume": 1259579.5697368474,
      "top_whale": {
        "address": "FjWzArnETRCpt3JxwyrFhzSYtKdzdiPRh8zVxWxhhBtQ",
        "volume": 296257.47743987804,
        "label": "FjWzAr...hBtQ"
      }
    },
    "top_txs": [
      {
        "hash": "5WLACDQxYSzhwCn6jp6dZa2rXBXoRPJhaofAyUJgUxb36vfQ4F258FPtusia8P8uP2BG4eugxUCSxHd219BLqqiL",
        "timestamp": "2025-12-19T04:01:08.000Z",
        "symbol": "USDC",
        "amount": 5996.165549,
        "amount_usd": 5996.618181548797,
        "from": "DnFbZyh9izWi9jAztMyJvjpK7TCi2GuVq8CajrUwpxMJ",
        "to": "Czfq3xZZDmsdGdUyrNLtRhGc47cXcZtLG4crryfu44zE",
        "from_label": "DnFbZy...",
        "to_label": "Orca Whirlpool",
        "signal": "BEARISH_OUTFLOW",
        "chain": "SOL"
      },
      {
        "hash": "eLd3RkerZZRetU7iUQ9Er2rUfXHrKLbsv12TDojLQpvFjyRk2qJnHQy6sXasmsnL2m3G4CAjLcsyEqs2fwKeLb8",
        "timestamp": "2025-12-19T04:01:05.000Z",
        "symbol": "USDC",
        "amount": 9178.336079,
        "amount_usd": 9179.028924055596,
        "from": "AE861PyrYJXm2TuxiMc8Ecwo4YYgAHfcYum3GWpSRFe3",
        "to": "6NUiVmsNjsi4AfsMsEiaezsaV9N4N1ZrD4jEnuWNRvyb",
        "from_label": "AE861P...",
        "to_label": "Orca Whirlpool",
        "signal": "BULLISH_INFLOW",
        "chain": "SOL"
      },
      {
        "hash": "2RQbV8wYPsMDoB1sPxVMAd5xvaxpbmHKoGTZuTANWfAF37kwGtowQpWDuU4guW9VkuLA5bYxGFypAqPHgBHjiW5B",
        "timestamp": "2025-12-19T04:01:05.000Z",
        "symbol": "USDC",
        "amount": 9830.381484,
        "amount_usd": 9831.123550007082,
        "from": "MfDuWeqSHEqTFVYZ7LoexgAK9dxk7cy4DFJWjWMGVWa",
        "to": "Czfq3xZZDmsdGdUyrNLtRhGc47cXcZtLG4crryfu44zE",
        "from_label": "MfDuWe...",
        "to_label": "Orca Whirlpool",
        "signal": "BULLISH_INFLOW",
        "chain": "SOL"
      },
      {
        "hash": "2xZQ4Jp2fv76i1S2xtCUSNnGGpe7EpgxgqDwaTF5xkdudSLBA8tLVLUnwya2rXa6uTUBGxraa4ZHTuEnUNeQXrU4",
        "timestamp": "2025-12-19T04:01:05.000Z",
        "symbol": "USDC",
        "amount": 33083.163672,
        "amount_usd": 33085.66102077611,
        "from": "BMnT51N4iSNhWU5PyFFgWwFvN1jgaiiDr9ZHgnkm3iLJ",
        "to": "BVRbyLjjfSBcoyiYFuxbgKYnWuiFaF9CSXEa5vdSZ9Hh",
        "from_label": "BMnT51...",
        "to_label": "Meteora DLMM",
        "signal": "BULLISH_INFLOW",
        "chain": "SOL"
      },
      {
        "hash": "mG2N8KkppZHioJQUdaQWuR1C4srq2CrfpuKvtB7YmoUMVdCvV5FBhNkCkfp15WxoaD6TZRM8ZKJK7ghS8V6qbS1",
        "timestamp": "2025-12-19T04:01:05.000Z",
        "symbol": "USDC",
        "amount": 19941.335675,
        "amount_usd": 19942.840986606097,
        "from": "BMnT51N4iSNhWU5PyFFgWwFvN1jgaiiDr9ZHgnkm3iLJ",
        "to": "BGm1tav58oGcsQJehL9WXBFXF7D27vZsKefj4xJKD5Y",
        "from_label": "BMnT51...",
        "to_label": "Meteora DLMM",
        "signal": "BULLISH_INFLOW",
        "chain": "SOL"
      },
      {
        "hash": "4ziMgS1Eyp8PPUfkskVfrhZawbBwQDoJdJBvWT45pVpo73TaSta1TMn7Bx8XT1NgensMZJntpXvgF7chNn1NU5dD",
        "timestamp": "2025-12-19T04:01:04.000Z",
        "symbol": "USDC",
        "amount": 6666.666666,
        "amount_usd": 6667.169912666616,
        "from": "JA6br2dFCkmKuiKXCsw5pinx5FrYHqR8eNCMydBp4Qr5",
        "to": "6NUiVmsNjsi4AfsMsEiaezsaV9N4N1ZrD4jEnuWNRvyb",
        "from_label": "JA6br2...",
        "to_label": "Orca Whirlpool",
        "signal": "BULLISH_INFLOW",
        "chain": "SOL"
      },
      {
        "hash": "2QLx5FT9ViDqR5DiJPfwVjWmbcNbjx1y3FfCwcspvFUgs1Sw5hgpajyJYPsptrPydyZLF6bqDXom6quLtrHedE3P",
        "timestamp": "2025-12-19T04:01:04.000Z",
        "symbol": "USDC",
        "amount": 6470.931398,
        "amount_usd": 6471.41986919844,
        "from": "GRV6aYozLxNaH1Yj6T2h2qfEog9ctssas6brwCcbuSK5",
        "to": "Czfq3xZZDmsdGdUyrNLtRhGc47cXcZtLG4crryfu44zE",
        "from_label": "GRV6aY...",
        "to_label": "Orca Whirlpool",
        "signal": "BULLISH_INFLOW",
        "chain": "SOL"
      },
      {
        "hash": "4DjFWD2vfXcyDuFLZVfGCUABfEhrXoFfyFhZbbWkKjWs4xgBNKhEUqHKkDRpudLuRMhTtJnVdWGVgQHvUnDgrm3H",
        "timestamp": "2025-12-19T04:01:03.000Z",
        "symbol": "USDC",
        "amount": 15915.590178,
        "amount_usd": 15916.791598155765,
        "from": "BMnT51N4iSNhWU5PyFFgWwFvN1jgaiiDr9ZHgnkm3iLJ",
        "to": "Czfq3xZZDmsdGdUyrNLtRhGc47cXcZtLG4crryfu44zE",
        "from_label": "BMnT51...",
        "to_label": "Orca Whirlpool",
        "signal": "BULLISH_INFLOW",
        "chain": "SOL"
      },
      {
        "hash": "4hrhuhz7hn5V5z57aqX33sZo9jgKozWYzuwi1LuuDwXgY4hxgtxdCbdVYzi8gDNrgEeqnemVF7zPhEr5x4xu3S2P",
        "timestamp": "2025-12-19T04:01:03.000Z",
        "symbol": "USDC",
        "amount": 6760.292652,
        "amount_usd": 6760.802966211421,
        "from": "GRV6aYozLxNaH1Yj6T2h2qfEog9ctssas6brwCcbuSK5",
        "to": "Czfq3xZZDmsdGdUyrNLtRhGc47cXcZtLG4crryfu44zE",
        "from_label": "GRV6aY...",
        "to_label": "Orca Whirlpool",
        "signal": "BULLISH_INFLOW",
        "chain": "SOL"
      },
      {
        "hash": "5faQFqTGXkVZGZmvMgg4z2nHxhBJiqdzDKM36jAg3qFqPCteAMoefPHBJkZ7LtVcDXYtT4MoU6yTFGhpWnFLPvu",
        "timestamp": "2025-12-19T04:01:03.000Z",
        "symbol": "USDC",
        "amount": 16593.245577,
        "amount_usd": 16594.498151328873,
        "from": "GRV6aYozLxNaH1Yj6T2h2qfEog9ctssas6brwCcbuSK5",
        "to": "Czfq3xZZDmsdGdUyrNLtRhGc47cXcZtLG4crryfu44zE",
        "from_label": "GRV6aY...",
        "to_label": "Orca Whirlpool",
        "signal": "BULLISH_INFLOW",
        "chain": "SOL"
      },
      {
        "hash": "4nuQbFp4LAeX6zSFRGZZtc6L7VJhegZ5oUHKN5o2Ax4k1KxxweNrX3RYAxAeBvYSPgNdUywhwhAc1PJhaTVPSRSu",
        "timestamp": "2025-12-19T04:01:03.000Z",
        "symbol": "USDC",
        "amount": 5645.318439,
        "amount_usd": 5645.744587153004,
        "from": "MfDuWeqSHEqTFVYZ7LoexgAK9dxk7cy4DFJWjWMGVWa",
        "to": "Czfq3xZZDmsdGdUyrNLtRhGc47cXcZtLG4crryfu44zE",
        "from_label": "MfDuWe...",
        "to_label": "Orca Whirlpool",
        "signal": "BULLISH_INFLOW",
        "chain": "SOL"
      },
      {
        "hash": "uXAnR7MxGdpKrLZ1zhCkrBBNHaz6oC1i52kqjHzo1B3hB7n4BfcfqtRaBM6fxzfZVAFjLCVxbBnpoTQ1dYs1mFd",
        "timestamp": "2025-12-19T04:01:03.000Z",
        "symbol": "USDC",
        "amount": 19345.007723,
        "amount_usd": 19346.46801959798,
        "from": "93U65rT9tdPCwzpXVp4o6FUax7w4nmxtat44nmZtqV3x",
        "to": "Czfq3xZZDmsdGdUyrNLtRhGc47cXcZtLG4crryfu44zE",
        "from_label": "93U65r...",
        "to_label": "Orca Whirlpool",
        "signal": "BULLISH_INFLOW",
        "chain": "SOL"
      },
      {
        "hash": "4bU7VcD4yCBVhvwtT9vfi2tvMEi4dyoM2qpp3iLkRkvfKYmwHK7v9UWi8qvsgB8yZySjacWizMz9XAf8gvB9ZCgi",
        "timestamp": "2025-12-19T04:01:03.000Z",
        "symbol": "USDC",
        "amount": 5033.479691,
        "amount_usd": 5033.859653281434,
        "from": "GRV6aYozLxNaH1Yj6T2h2qfEog9ctssas6brwCcbuSK5",
        "to": "Czfq3xZZDmsdGdUyrNLtRhGc47cXcZtLG4crryfu44zE",
        "from_label": "GRV6aY...",
        "to_label": "Orca Whirlpool",
        "signal": "BULLISH_INFLOW",
        "chain": "SOL"
      },
      {
        "hash": "Ah6DCeniPoSeMDcgUFS6UorU8KRXfrrnYpSwdcmPXsWhun7tzH3HzNTEygDZ4Umw8PEfTFL7GJpp4dpWDwAsCyp",
        "timestamp": "2025-12-19T04:00:52.000Z",
        "symbol": "SOL",
        "amount": 46.83778755,
        "amount_usd": 5685.3626877479555,
        "from": "HuTshmtwcQkWBLzgW3m4uwcmik7Lmz4YFpYcTqMJpXiP",
        "to": "HktfL7iwGKT5QHjywQkcDnZXScoh811k7akrMZJkCcEF",
        "from_label": "HuTshm...",
        "to_label": "Orca Whirlpool",
        "signal": "BEARISH_INFLOW",
        "chain": "SOL"
      },
      {
        "hash": "5Y1mhgZhcYbSTjzyCz4p1jdWLRWDyMJqwFNY4kHXn9zbRWo29MNbFHsgMuDi8APvfQBx3k8FxPdnn6msYkdbvtfR",
        "timestamp": "2025-12-19T04:00:52.000Z",
        "symbol": "USDC",
        "amount": 6885.015947,
        "amount_usd": 6885.5356761987905,
        "from": "3n7fQVEeSVoKUgArBt3xMwrMej8Koe4rRekb19SeUjwj",
        "to": "Czfq3xZZDmsdGdUyrNLtRhGc47cXcZtLG4crryfu44zE",
        "from_label": "3n7fQV...",
        "to_label": "Orca Whirlpool",
        "signal": "BULLISH_INFLOW",
        "chain": "SOL"
      },
      {
        "hash": "uvTEmeeKSkBQ4nTR9xqq43mdRbJPEut9p1UPcGjPdTWdqGGzk9weCxAtjMnMtafrsLf6cf3haJfN9AcEgMUCMPQ",
        "timestamp": "2025-12-19T04:00:52.000Z",
        "symbol": "USDC",
        "amount": 5120.0,
        "amount_usd": 5120.38649344,
        "from": "3y5u6tGmYwoFpLgfRYcjxRLj6g4FYHfoG3Z3g4ChGas5",
        "to": "6NUiVmsNjsi4AfsMsEiaezsaV9N4N1ZrD4jEnuWNRvyb",
        "from_label": "3y5u6t...",
        "to_label": "Orca Whirlpool",
        "signal": "BULLISH_INFLOW",
        "chain": "SOL"
      },
      {
        "hash": "4FNM82WEcZYoYSVTEt5QgDPjtM3SJMQD4hNEfwEm6yptqeFnXWR64ZN1bMaJqiT8pafTGQWwRiSTu5h6VuptzyfD",
        "timestamp": "2025-12-19T04:00:37.000Z",
        "symbol": "USDC",
        "amount": 6593.56833,
        "amount_usd": 6594.066058692526,
        "from": "AAvdewt71kkde2segr6gYnNemhNLfokyZpdzwwi4yDfm",
        "to": "6NUiVmsNjsi4AfsMsEiaezsaV9N4N1ZrD4jEnuWNRvyb",
        "from_label": "AAvdew...",
        "to_label": "Orca Whirlpool",
        "signal": "BEARISH_OUTFLOW",
        "chain": "SOL"
      },
      {
        "hash": "5eDoyddcBrBxgVKDu5G4rqN6F5vcrCokUbt6jmMYi1CYZuABGnReLzyBWqJkvhBFJdZCjGbrWe8iyxt4e2TS9PPc",
        "timestamp": "2025-12-19T04:00:29.000Z",
        "symbol": "USDC",
        "amount": 5334.266626,
        "amount_usd": 5334.6692937847965,
        "from": "3n7fQVEeSVoKUgArBt3xMwrMej8Koe4rRekb19SeUjwj",
        "to": "Czfq3xZZDmsdGdUyrNLtRhGc47cXcZtLG4crryfu44zE",
        "from_label": "3n7fQV...",
        "to_label": "Orca Whirlpool",
        "signal": "BULLISH_INFLOW",
        "chain": "SOL"
      },
      {
        "hash": "5hzVrVdgDuaRUaMnp747pQAgoBVT5g7WZT5kr3LK5HDgcCeeku2fNaDyyHZTdsjkYiyxWWhcT9umM8aQu6NCYNF3",
        "timestamp": "2025-12-19T04:00:26.000Z",
        "symbol": "USDC",
        "amount": 5970.91741,
        "amount_usd": 5971.368136642528,
        "from": "3n7fQVEeSVoKUgArBt3xMwrMej8Koe4rRekb19SeUjwj",
        "to": "Czfq3xZZDmsdGdUyrNLtRhGc47cXcZtLG4crryfu44zE",
        "from_label": "3n7fQV...",
        "to_label": "Orca Whirlpool",
        "signal": "BULLISH_INFLOW",
        "chain": "SOL"
      },
      {
        "hash": "iJkDsDQK2LbmTutsER2AdmjHLfxduFVFiHJyMZVD14xoejS1upYiZHtR6a8u2F4bVvS3XSksCVfBmWuAfYxBtVj",
        "timestamp": "2025-12-19T04:00:19.000Z",
        "symbol": "USDC",
        "amount": 10990.665845,
        "amount_usd": 10991.49549739264,
        "from": "CreQJ2t94QK5dsxUZGXfPJ8Nx7wA9LHr5chxjSMkbNft",
        "to": "Czfq3xZZDmsdGdUyrNLtRhGc47cXcZtLG4crryfu44zE",
        "from_label": "CreQJ2...",
        "to_label": "Orca Whirlpool",
        "signal": "BEARISH_OUTFLOW",
        "chain": "SOL"
      },
      {
        "hash": "4aRYL3SGnQaarZZfG7bGjC7HJ2hUgvTE6V4k2NZJr9ANaaR7DwDewxfduXsAubcmYwLJJgmbh9gkGMGJ4B6Lbp8z",
        "timestamp": "2025-12-19T04:00:14.000Z",
        "symbol": "USDC",
        "amount": 21980.872365,
        "amount_usd": 21982.531635112213,
        "from": "CreQJ2t94QK5dsxUZGXfPJ8Nx7wA9LHr5chxjSMkbNft",
        "to": "Czfq3xZZDmsdGdUyrNLtRhGc47cXcZtLG4crryfu44zE",
        "from_label": "CreQJ2...",
        "to_label": "Orca Whirlpool",
        "signal": "BEARISH_OUTFLOW",
        "chain": "SOL"
      },
      {
        "hash": "2121cdJVFiBJ5uQFTuDGDFnB6jYEUJcURs9WPddgCJSowab7o4N3CS9Ho5PQXuFkZMDSLnRkfhVyc9W3coYiayh2",
        "timestamp": "2025-12-19T04:00:12.000Z",
        "symbol": "USDC",
        "amount": 5995.315354,
        "amount_usd": 5995.767922370127,
        "from": "CreQJ2t94QK5dsxUZGXfPJ8Nx7wA9LHr5chxjSMkbNft",
        "to": "Czfq3xZZDmsdGdUyrNLtRhGc47cXcZtLG4crryfu44zE",
        "from_label": "CreQJ2...",
        "to_label": "Orca Whirlpool",
        "signal": "BEARISH_OUTFLOW",
        "chain": "SOL"
      },
      {
        "hash": "5GtjR972EsGXPPhnsuq2Vq26AsXWncLqvQ3nCnbc1UUVzqdjgoFNnd7KB8HAtiPkRM7Fe2xckyRCRVgByum3JCYo",
        "timestamp": "2025-12-18T23:58:56.000Z",
        "symbol": "SOL",
        "amount": 79.547151353,
        "amount_usd": 9505.127312916578,
        "from": "128mNG5nS3Mrj44Hfeo8v9RrihFh6wKWSdDcsXXzvaRD",
        "to": "Da973EFJKpJau8He4X5AkwJkTq8D4K4kRS5uXqpthxjK",
        "from_label": "128mNG...",
        "to_label": "Raydium CLMM",
        "signal": "BULLISH_OUTFLOW",
        "chain": "SOL"
      },
      {
        "hash": "5tXrqpkZFtBduHHKhZe6AgBbk6WjT2QQSN4CLoBijfMos6fKK5sHCUioYYGUnV68dmXjfdp8UmAzKP353nyEW5Do",
        "timestamp": "2025-12-18T23:58:35.000Z",
        "symbol": "USDC",
        "amount": 8189.500934,
        "amount_usd": 8188.77369812756,
        "from": "HxjwdF326ZunmUwC1iXhfgL3ku78YsksN6n7Rfxzwr6b",
        "to": "3ucNos4NbumPLZNWztqGHNFFgkHeRMBQAVemeeomsUxv",
        "from_label": "HxjwdF...",
        "to_label": "Raydium CLMM",
        "signal": "BULLISH_INFLOW",
        "chain": "SOL"
      },
      {
        "hash": "5GJSTswDMKJ71Q2Tiaa24RtNPUCwdwwyvybf9XeJEur15NrJeo9qTsprxeYxV9gWYewRUxmBJSk1X2uHyXsz7Dqq",
        "timestamp": "2025-12-18T23:58:35.000Z",
        "symbol": "USDC",
        "amount": 10060.423679,
        "amount_usd": 10059.53030331688,
        "from": "5fsHC3TPRaQotT41uVBbWoXWMv4x5WxebcG6ZJjBnDHX",
        "to": "3ucNos4NbumPLZNWztqGHNFFgkHeRMBQAVemeeomsUxv",
        "from_label": "5fsHC3...",
        "to_label": "Raydium CLMM",
        "signal": "BEARISH_OUTFLOW",
        "chain": "SOL"
      },
      {
        "hash": "uoLoZbK6yL7P32HsxkehYeuiMxqqy9qtACjqyjsFeuPvC5YvobNVHD5xXfwxPaCm15kcBnPsmqVbhEpS4QABa3o",
        "timestamp": "2025-12-18T23:55:55.000Z",
        "symbol": "USDC",
        "amount": 11323.287552,
        "amount_usd": 11322.282032742094,
        "from": "7dGrdJRYtsNR8UYxZ3TnifXGjGc9eRYLq9sELwYpuuUu",
        "to": "Czfq3xZZDmsdGdUyrNLtRhGc47cXcZtLG4crryfu44zE",
        "from_label": "7dGrdJ...",
        "to_label": "Orca Whirlpool",
        "signal": "BULLISH_INFLOW",
        "chain": "SOL"
      },
      {
        "hash": "4eSbs9ooEb5gNPY559M9R3Yx37WHZNUDM39yxMPhKuT69mBgUisGTsPdDisgrAjw5Ua5ixrP22JNStyaK8SdiTFp",
        "timestamp": "2025-12-18T23:55:41.000Z",
        "symbol": "USDC",
        "amount": 5183.538121,
        "amount_usd": 5183.077817631317,
        "from": "CEEXTqHaqbVriXoW4uvdaPShkMaHg9AWnFXLS1nS887C",
        "to": "Czfq3xZZDmsdGdUyrNLtRhGc47cXcZtLG4crryfu44zE",
        "from_label": "CEEXTq...",
        "to_label": "Orca Whirlpool",
        "signal": "BEARISH_OUTFLOW",
        "chain": "SOL"
      },
      {
        "hash": "5YiuYkZMS8hxqmHCuHiU4RzXKh425vwCWcu9duUhbsAj7Fhofq6myJVARNFSWC9VVLfS2NMSXNC7mK2aJnkfroXb",
        "timestamp": "2025-12-18T20:00:47.000Z",
        "symbol": "USDC",
        "amount": 10000.0,
        "amount_usd": 9999.99999,
        "from": "YubFizptp3MXUAtZmqkRS9DyCkMeZaVwiaRCGBTxayo",
        "to": "9d9mb8kooFfaD3SctgZtkxQypkshx6ezhbKio89ixyy2",
        "from_label": "YubFiz...",
        "to_label": "Meteora DLMM",
        "signal": "BULLISH_INFLOW",
        "chain": "SOL"
      },
      {
        "hash": "2rLS8vHGkQg2q75wfuto1uAVupJVievihtEQSiKE3b5RJEb1JK2vuXVcg8g9shP2qBDvRaD9ULEH4NrJAVLNYuUJ",
        "timestamp": "2025-12-18T20:00:47.000Z",
        "symbol": "USDC",
        "amount": 40000.0,
        "amount_usd": 39999.99996,
        "from": "YubFizptp3MXUAtZmqkRS9DyCkMeZaVwiaRCGBTxayo",
        "to": "9d9mb8kooFfaD3SctgZtkxQypkshx6ezhbKio89ixyy2",
        "from_label": "YubFiz...",
        "to_label": "Meteora DLMM",
        "signal": "BULLISH_INFLOW",
        "chain": "SOL"
      },
      {
        "hash": "5ktjBoxsrmVGAnHTYd91SjuMi7UWnSxjZow326f4bcbjabkLKovvmrF5ifvVa5BVLx47n2HpiMtjwjiNFGBivdEf",
        "timestamp": "2025-12-18T20:00:47.000Z",
        "symbol": "USDC",
        "amount": 40000.0,
        "amount_usd": 39999.99996,
        "from": "YubFizptp3MXUAtZmqkRS9DyCkMeZaVwiaRCGBTxayo",
        "to": "9d9mb8kooFfaD3SctgZtkxQypkshx6ezhbKio89ixyy2",
        "from_label": "YubFiz...",
        "to_label": "Meteora DLMM",
        "signal": "BULLISH_INFLOW",
        "chain": "SOL"
      },
      {
        "hash": "5Z46RgmTKq8ZdG3PBeAHu6Z8avbQ3JEybPjk295bPDSZ3sLQTQBD2avNVZxSxXgJgEiysJHNeMzrCwz2s18Cq1iu",
        "timestamp": "2025-12-18T20:00:45.000Z",
        "symbol": "USDC",
        "amount": 8422.544519,
        "amount_usd": 8422.544510577454,
        "from": "BMnT51N4iSNhWU5PyFFgWwFvN1jgaiiDr9ZHgnkm3iLJ",
        "to": "BGm1tav58oGcsQJehL9WXBFXF7D27vZsKefj4xJKD5Y",
        "from_label": "BMnT51...",
        "to_label": "Meteora DLMM",
        "signal": "BULLISH_INFLOW",
        "chain": "SOL"
      },
      {
        "hash": "pTpqBYgt6BsBkhbnv4Yt5qKG3WH8hGVC3fNxc9PQLoU8QYDxGUY8WSBoSHpku9CBux7JQzrFb4L2Lju5J9Wr8s6",
        "timestamp": "2025-12-18T20:00:43.000Z",
        "symbol": "SOL",
        "amount": 150.018586721,
        "amount_usd": 17672.005468431053,
        "from": "yUwUyoufLrCmjcgURefVzvAfpcaZ2so6be4uDziT9aH",
        "to": "DxD41srN8Xk9QfYjdNXF9tTnP6qQxeF2bZF8s1eN62Pe",
        "from_label": "yUwUyo...",
        "to_label": "Orca Whirlpool",
        "signal": "BULLISH_OUTFLOW",
        "chain": "SOL"
      },
      {
        "hash": "2FWLNz9991zFHzdA9wy1JKsZ2Mqm1T75Vz9FHrtV4fe8YkZyHggSLGz1juWkgM1XTBVVL5ksdRox2mgYb1DJ8HhJ",
        "timestamp": "2025-12-18T20:00:43.000Z",
        "symbol": "USDC",
        "amount": 8395.894763,
        "amount_usd": 8395.894754604105,
        "from": "BMnT51N4iSNhWU5PyFFgWwFvN1jgaiiDr9ZHgnkm3iLJ",
        "to": "BGm1tav58oGcsQJehL9WXBFXF7D27vZsKefj4xJKD5Y",
        "from_label": "BMnT51...",
        "to_label": "Meteora DLMM",
        "signal": "BULLISH_INFLOW",
        "chain": "SOL"
      },
      {
        "hash": "doPSAUv9VitEvWZzFKFEbeuSVJt186WywEfeUHPb2V9yK5z9ZdXS9cReBUA26GsMza9BvWz5HFFKPfZE6kvF19K",
        "timestamp": "2025-12-18T20:00:43.000Z",
        "symbol": "SOL",
        "amount": 822.700404595,
        "amount_usd": 96913.09834775364,
        "from": "2W8gXg1eN3HLdL5iJbd3fhKBMsmk22zXJDrCycjwac1X",
        "to": "DxD41srN8Xk9QfYjdNXF9tTnP6qQxeF2bZF8s1eN62Pe",
        "from_label": "2W8gXg...",
        "to_label": "Orca Whirlpool",
        "signal": "BEARISH_INFLOW",
        "chain": "SOL"
      },
      {
        "hash": "5F1HZcgUc7mJhwpNn2w6JRpwizCfzhc5RGBWZ2dLmf2S21sL2H9tzLNTR7sY4EbZ86sLYRFbJVMZkL5t8MrwR6PM",
        "timestamp": "2025-12-18T20:00:39.000Z",
        "symbol": "USDC",
        "amount": 8454.502171,
        "amount_usd": 8454.502162545497,
        "from": "mxtUm5M5xDxoKNEhFTXfDpX1e5fE28cZ18F7KopgNLC",
        "to": "3ucNos4NbumPLZNWztqGHNFFgkHeRMBQAVemeeomsUxv",
        "from_label": "mxtUm5...",
        "to_label": "Raydium CLMM",
        "signal": "BEARISH_OUTFLOW",
        "chain": "SOL"
      },
      {
        "hash": "2dDMvSB9JreRvKEy4yGYrdobKD8qCBVWXqmwpa2riirwojtmgpvGCWKD88kBaPVatwXWqBUdBNR5MqvbMBCoC5RC",
        "timestamp": "2025-12-18T20:00:28.000Z",
        "symbol": "USDC",
        "amount": 6228.510808,
        "amount_usd": 6228.510801771489,
        "from": "93U65rT9tdPCwzpXVp4o6FUax7w4nmxtat44nmZtqV3x",
        "to": "Czfq3xZZDmsdGdUyrNLtRhGc47cXcZtLG4crryfu44zE",
        "from_label": "93U65r...",
        "to_label": "Orca Whirlpool",
        "signal": "BULLISH_INFLOW",
        "chain": "SOL"
      },
      {
        "hash": "HXrYGu8ha4CtEkCGU2vPv8eJT4YV9qk29FsNHAZ4eDNDER5NbhB7HM3fqccWXnNXt4LzU7tr94os2i3zVn5s2Am",
        "timestamp": "2025-12-18T20:00:28.000Z",
        "symbol": "USDC",
        "amount": 8768.481377,
        "amount_usd": 8768.48136823152,
        "from": "BMnT51N4iSNhWU5PyFFgWwFvN1jgaiiDr9ZHgnkm3iLJ",
        "to": "BGm1tav58oGcsQJehL9WXBFXF7D27vZsKefj4xJKD5Y",
        "from_label": "BMnT51...",
        "to_label": "Meteora DLMM",
        "signal": "BULLISH_INFLOW",
        "chain": "SOL"
      },
      {
        "hash": "3o98ojDdJt8PVvc1axbAdGua2oEuoRGpa9zcbufFBawfjQwvxnpg3jZU8C1FjMwVvR7TAx5xenohby34uHL8mgBM",
        "timestamp": "2025-12-18T16:01:11.000Z",
        "symbol": "USDC",
        "amount": 8000.000642,
        "amount_usd": 8000.99365807969,
        "from": "J2ANNaq4uUk3iUGoNijKCwXTReGLyg2yQpGcAZjzyBZG",
        "to": "3wijQvPKm6jHQrAkfPpok5o8WjCWPm1DGG17NmeW8q1w",
        "from_label": "J2ANNa...",
        "to_label": "Orca Whirlpool",
        "signal": "BEARISH_OUTFLOW",
        "chain": "SOL"
      },
      {
        "hash": "53YXtyN5dwZAbeNj4GNiru7KdCEMpiyfg9GgAtCfZvZGtKWWUc1oXDALdMNGZrKCtvEh98RCGjTiAftyMMAKtHYA",
        "timestamp": "2025-12-18T16:01:11.000Z",
        "symbol": "USDC",
        "amount": 5000.012052,
        "amount_usd": 5000.632688495979,
        "from": "J2ANNaq4uUk3iUGoNijKCwXTReGLyg2yQpGcAZjzyBZG",
        "to": "3wijQvPKm6jHQrAkfPpok5o8WjCWPm1DGG17NmeW8q1w",
        "from_label": "J2ANNa...",
        "to_label": "Orca Whirlpool",
        "signal": "BEARISH_OUTFLOW",
        "chain": "SOL"
      },
      {
        "hash": "3Af4ZAJMZP3K1aRBgFTgsfqUKGFRVYjJidxrWJh1h63MVzrNajhm3C2VxtarEACnuWicqKebe1pfCJbzsRv2Frff",
        "timestamp": "2025-12-18T16:01:11.000Z",
        "symbol": "USDC",
        "amount": 5000.021018,
        "amount_usd": 5000.6416556089025,
        "from": "J2ANNaq4uUk3iUGoNijKCwXTReGLyg2yQpGcAZjzyBZG",
        "to": "3wijQvPKm6jHQrAkfPpok5o8WjCWPm1DGG17NmeW8q1w",
        "from_label": "J2ANNa...",
        "to_label": "Orca Whirlpool",
        "signal": "BEARISH_OUTFLOW",
        "chain": "SOL"
      },
      {
        "hash": "3YiDrqtt49n9ack4PKgiCkoEkeM8gKFyTd2WCmULLvynDpViBMakEmRNdHvmq2tU5tvQWxFyT5FQEMhgsWL5m88w",
        "timestamp": "2025-12-18T16:01:11.000Z",
        "symbol": "USDC",
        "amount": 8000.052278,
        "amount_usd": 8001.045300489112,
        "from": "J2ANNaq4uUk3iUGoNijKCwXTReGLyg2yQpGcAZjzyBZG",
        "to": "3wijQvPKm6jHQrAkfPpok5o8WjCWPm1DGG17NmeW8q1w",
        "from_label": "J2ANNa...",
        "to_label": "Orca Whirlpool",
        "signal": "BEARISH_OUTFLOW",
        "chain": "SOL"
      },
      {
        "hash": "v8Jpc1xmXfVgp4fYTFPYM9UYzfNZ9nkFaopYLNWQpDfhRPUWy9Luz18Re6F2262gD8M589y3ybxpyXMdBNdDVFf",
        "timestamp": "2025-12-18T16:01:11.000Z",
        "symbol": "USDC",
        "amount": 8000.075226,
        "amount_usd": 8001.068251337579,
        "from": "J2ANNaq4uUk3iUGoNijKCwXTReGLyg2yQpGcAZjzyBZG",
        "to": "3wijQvPKm6jHQrAkfPpok5o8WjCWPm1DGG17NmeW8q1w",
        "from_label": "J2ANNa...",
        "to_label": "Orca Whirlpool",
        "signal": "BEARISH_OUTFLOW",
        "chain": "SOL"
      },
      {
        "hash": "4fgdxodKhbZr5DNPFu3Cxph7guuSbUTaMCdi11SShdSg1P3Lq1ZjKzkomGVKAzt7xYH9d7DzZ9YHCcK3cka54rM2",
        "timestamp": "2025-12-18T16:01:11.000Z",
        "symbol": "USDC",
        "amount": 5000.062254,
        "amount_usd": 5000.682896727403,
        "from": "J2ANNaq4uUk3iUGoNijKCwXTReGLyg2yQpGcAZjzyBZG",
        "to": "3wijQvPKm6jHQrAkfPpok5o8WjCWPm1DGG17NmeW8q1w",
        "from_label": "J2ANNa...",
        "to_label": "Orca Whirlpool",
        "signal": "BEARISH_OUTFLOW",
        "chain": "SOL"
      },
      {
        "hash": "2w8AyLL96cw3U2JbenrqqPc4dHfbT1pYxxFYWKAh6BJbQxDVXDM3v53Di5BEqGtPJNC2RTffjpdEv6u1ReuZ4ejH",
        "timestamp": "2025-12-18T16:01:11.000Z",
        "symbol": "USDC",
        "amount": 5000.071219,
        "amount_usd": 5000.691862840202,
        "from": "J2ANNaq4uUk3iUGoNijKCwXTReGLyg2yQpGcAZjzyBZG",
        "to": "3wijQvPKm6jHQrAkfPpok5o8WjCWPm1DGG17NmeW8q1w",
        "from_label": "J2ANNa...",
        "to_label": "Orca Whirlpool",
        "signal": "BEARISH_OUTFLOW",
        "chain": "SOL"
      },
      {
        "hash": "WRuWZjQvXnHDuzidwpJgR58LpU7a9BmW8WnqJjs6uHt2PtHrF8fA3vYBXncapx2pwu2BGNw5CHWBtBEMHRYD5ox",
        "timestamp": "2025-12-18T16:01:11.000Z",
        "symbol": "USDC",
        "amount": 5849.47135,
        "amount_usd": 5850.197427330262,
        "from": "3n7fQVEeSVoKUgArBt3xMwrMej8Koe4rRekb19SeUjwj",
        "to": "Czfq3xZZDmsdGdUyrNLtRhGc47cXcZtLG4crryfu44zE",
        "from_label": "3n7fQV...",
        "to_label": "Orca Whirlpool",
        "signal": "BULLISH_INFLOW",
        "chain": "SOL"
      },
      {
        "hash": "5XT9iAMiVMj3NM9g76XeXA3gNK4HxBH5EqiJVAeAcJebgHDejv6AVpyWuMuTRx3RNCmTAmbmKt9RknxzYT4sPN3u",
        "timestamp": "2025-12-18T16:01:11.000Z",
        "symbol": "USDC",
        "amount": 14376.395659,
        "amount_usd": 14378.180157863966,
        "from": "GRV6aYozLxNaH1Yj6T2h2qfEog9ctssas6brwCcbuSK5",
        "to": "Czfq3xZZDmsdGdUyrNLtRhGc47cXcZtLG4crryfu44zE",
        "from_label": "GRV6aY...",
        "to_label": "Orca Whirlpool",
        "signal": "BULLISH_INFLOW",
        "chain": "SOL"
      },
      {
        "hash": "65yQ5ZnYm1qqGRnkBmDw85YMK2bHDNkFXzY2FzhZiMniU2BkNg4wEXDj65gM2AEsTz3iPM85igqgSF5f3cerEWP5",
        "timestamp": "2025-12-18T16:01:11.000Z",
        "symbol": "USDC",
        "amount": 5610.123808,
        "amount_usd": 5610.820175837916,
        "from": "BMnT51N4iSNhWU5PyFFgWwFvN1jgaiiDr9ZHgnkm3iLJ",
        "to": "5rCf1DM8LjKTw4YqhnoLcngyZYeNnQqztScTogYHAS6",
        "from_label": "BMnT51...",
        "to_label": "Meteora DLMM",
        "signal": "BULLISH_INFLOW",
        "chain": "SOL"
      },
      {
        "hash": "26yUjhzxBThgbyFaUJ1JUpaR7oQKxvqtDS2hWacQC9bbWaxeXnez2vV4GeKesogAEcudYQ5tDxpMAm9oAyVZY1vo",
        "timestamp": "2025-12-18T16:01:11.000Z",
        "symbol": "USDC",
        "amount": 6933.338029,
        "amount_usd": 6934.198643449526,
        "from": "GRV6aYozLxNaH1Yj6T2h2qfEog9ctssas6brwCcbuSK5",
        "to": "3ucNos4NbumPLZNWztqGHNFFgkHeRMBQAVemeeomsUxv",
        "from_label": "GRV6aY...",
        "to_label": "Raydium CLMM",
        "signal": "BULLISH_INFLOW",
        "chain": "SOL"
      },
      {
        "hash": "2pXcnfSHkgk37gwhdrcGyWkcHHxMii8ywj7FXLc9Y9yHLp7UrfDbJ2NBHUJoz2mMToET3Zhy6ojfut4EvAPZMk2U",
        "timestamp": "2025-12-18T16:01:11.000Z",
        "symbol": "USDC",
        "amount": 11802.608501,
        "amount_usd": 11804.073523385405,
        "from": "3n7fQVEeSVoKUgArBt3xMwrMej8Koe4rRekb19SeUjwj",
        "to": "Czfq3xZZDmsdGdUyrNLtRhGc47cXcZtLG4crryfu44zE",
        "from_label": "3n7fQV...",
        "to_label": "Orca Whirlpool",
        "signal": "BULLISH_INFLOW",
        "chain": "SOL"
      },
      {
        "hash": "4X6sPNAKJrHrCApJsTr12L43WSodtrq24Kjc2LZjuLunmX9c5WFw6kSChYhbfXZituXEWUqn3C4tfU1XbytUqHfX",
        "timestamp": "2025-12-18T16:01:10.000Z",
        "symbol": "USDC",
        "amount": 296220.708452,
        "amount_usd": 296257.47743987804,
        "from": "FjWzArnETRCpt3JxwyrFhzSYtKdzdiPRh8zVxWxhhBtQ",
        "to": "6fteKNvMdv7tYmBoJHhj1jx6rHcEwC6RdSEmVpyS613J",
        "from_label": "FjWzAr...",
        "to_label": "Orca Whirlpool",
        "signal": "BEARISH_OUTFLOW",
        "chain": "SOL"
      }
    ]
  },
  "fear_greed": {
    "value": 16,
    "value_classification": "Extreme Fear"
  },
  "updated_at": "2025-12-19T12:01:49.097621",
  "ai_summary": {
    "en": "Amidst an 'Extreme Fear' macro market sentiment (BTC Fear & Greed Index at 16), whale activity on ETH and SOL chains presents a fascinating divergence.\n\n**ETH (Smart Money) Whale Sentiment:**\n*   **Short-term (24h):** ETH whales are showing a clear increase in bullish sentiment, with the sentiment score rising to 0.224. This is supported by substantial stablecoin net inflows of +$14.8M and token net inflows of +$1.24M, indicating active accumulation or readiness to deploy capital. The high average transaction size ($1.6M) and significant total volume ($103M), driven by 59 whales, confirm large-scale institutional interest. The top whale alone contributed $41M, signaling strong conviction.\n*   **Mid-term (7d):** While the mid-term sentiment score (0.07) is more neutral, the sharp uptick in 24h sentiment suggests smart money is increasingly turning bullish, likely viewing current market conditions as a strategic accumulation phase.\n\n**SOL (Retail/Speculative) Whale Sentiment:**\n*   **Short-term (24h):** SOL whales remain generally bullish (sentiment score 0.421) but show a slight cooling compared to the mid-term. A notable stablecoin net outflow of -$333.8K suggests some profit-taking or reallocation of capital out of stablecoins on the chain. Token net flow remains positive but small (+86.1K). Activity is driven by 28 whales, with a significantly smaller average transaction size ($17.5K) and total volume ($1.25M) compared to ETH, aligning with its 'Retail/Speculative' profile.\n*   **Mid-term (7d):** The 7d sentiment score of 0.48 indicates a strong bullish bias has persisted mid-term, although the 24h sentiment slightly moderated from this peak.\n\n**Comparison & Trends:**\nETH whales are demonstrating a contrarian accumulation strategy, with rapidly increasing bullish sentiment and significant capital inflows in a fearful market. This 'smart money' seems to be positioning for potential upside. In contrast, SOL whales, while generally bullish, show signs of short-term profit-taking or rotation (stablecoin outflow) despite a sustained mid-term bullishness, suggesting less conviction or potentially a more agile, speculative approach.\n\n**Short-Term Outlook:**\nGiven the 'Extreme Fear' macro backdrop, ETH appears to be garnering strong support and accumulation from large, institutional players. The increasing bullish sentiment and substantial stablecoin inflows suggest that smart money sees value and is actively buying or preparing to buy into the dip. This could provide strong underlying support for ETH and potentially lead to outperformance in the immediate short term. SOL, while still enjoying a bullish mid-term sentiment, faces slight short-term moderation and stablecoin outflows, which could make it more susceptible to volatility or a temporary pause as some speculative capital is redistributed or taken off the table. The short-term edge leans towards ETH, fueled by confident, contrarian whale accumulation."
  }
}